rnapy/__init__.py
rnapy/__main__.py
rnapy/cli.py
rnapy/toolkit.py
rnapy/core/__init__.py
rnapy/core/base.py
rnapy/core/config.py
rnapy/core/config_loader.py
rnapy/core/exceptions.py
rnapy/core/factory.py
rnapy/data/__init__.py
rnapy/data/dataset_downloader.py
rnapy/interfaces/__init__.py
rnapy/interfaces/inverse_folding.py
rnapy/interfaces/msa_analysis.py
rnapy/interfaces/sequence_analysis.py
rnapy/interfaces/structure_prediction.py
rnapy/providers/__init__.py
rnapy/providers/RiboDiffusion/__init__.py
rnapy/providers/RiboDiffusion/adapter.py
rnapy/providers/RiboDiffusion/config.py
rnapy/providers/RiboDiffusion/run_lib.py
rnapy/providers/RiboDiffusion/sampling.py
rnapy/providers/RiboDiffusion/utils.py
rnapy/providers/RiboDiffusion/diffusion/__init__.py
rnapy/providers/RiboDiffusion/diffusion/noise_schedule.py
rnapy/providers/RiboDiffusion/models/GVP_diff.py
rnapy/providers/RiboDiffusion/models/__init__.py
rnapy/providers/RiboDiffusion/models/ema.py
rnapy/providers/RiboDiffusion/models/esm_block.py
rnapy/providers/RiboDiffusion/models/esm_utils.py
rnapy/providers/RiboDiffusion/models/transformer_layer.py
rnapy/providers/RiboDiffusion/models/utils.py
rnapy/providers/lddt/__init__.py
rnapy/providers/lddt/lddt.py
rnapy/providers/lddt/ms.py
rnapy/providers/rhodesign/RhoDesign.py
rnapy/providers/rhodesign/RhoDesign_without2d.py
rnapy/providers/rhodesign/__init__.py
rnapy/providers/rhodesign/adapter.py
rnapy/providers/rhodesign/alphabet.py
rnapy/providers/rhodesign/config.py
rnapy/providers/rhodesign/gvp_transformer_encoder.py
rnapy/providers/rhodesign/gvp_transformer_encoder_without2d.py
rnapy/providers/rhodesign/util.py
rnapy/providers/rhodesign/gvp_src/__init__.py
rnapy/providers/rhodesign/gvp_src/features.py
rnapy/providers/rhodesign/gvp_src/gvp_encoder.py
rnapy/providers/rhodesign/gvp_src/gvp_modules.py
rnapy/providers/rhodesign/transformer_src/__init__.py
rnapy/providers/rhodesign/transformer_src/multihead_attention.py
rnapy-3.2.2.dist-info/licenses/LICENSE
rnapy-3.2.2.dist-info/METADATA
rnapy-3.2.2.dist-info/WHEEL
rnapy-3.2.2.dist-info/entry_points.txt
rnapy-3.2.2.dist-info/top_level.txt
rnapy-3.2.2.dist-info/RECORD
