Metadata-Version: 2.4
Name: rnapy
Version: 3.2.2
Summary: Unified RNA Analysis Toolkit - ML-powered RNA sequence analysis and structure prediction
Home-page: https://github.com/linorman/rnapy
Author: Linorman
Author-email: Linorman <zyh52616@gmail.com>
License: MIT
Project-URL: Homepage, https://github.com/linorman/rnapy
Project-URL: Repository, https://github.com/linorman/rnapy
Project-URL: Bug Reports, https://github.com/linorman/rnapy/issues
Project-URL: Documentation, https://github.com/linorman/rnapy/blob/main/README.md
Keywords: RNA,bioinformatics,machine-learning,structure-prediction,sequence-analysis
Classifier: Development Status :: 4 - Beta
Classifier: Intended Audience :: Science/Research
Classifier: Topic :: Scientific/Engineering :: Bio-Informatics
Classifier: Topic :: Scientific/Engineering :: Artificial Intelligence
Classifier: Programming Language :: Python :: 3
Classifier: Programming Language :: Python :: 3.8
Classifier: Programming Language :: Python :: 3.9
Classifier: Programming Language :: Python :: 3.10
Classifier: Programming Language :: Python :: 3.11
Classifier: Programming Language :: Python :: 3.12
Classifier: License :: OSI Approved :: MIT License
Classifier: Operating System :: OS Independent
Requires-Python: >=3.8
License-File: LICENSE
Requires-Dist: torch
Requires-Dist: torchvision
Requires-Dist: torchaudio
Requires-Dist: torch-cluster
Requires-Dist: torch-geometric
Requires-Dist: torch-scatter
Requires-Dist: numpy~=2.2.5
Requires-Dist: scipy>=1.12.0
Requires-Dist: pandas>=1.3.0
Requires-Dist: scikit-learn>=0.24.0
Requires-Dist: numexpr
Requires-Dist: bottleneck
Requires-Dist: numba
Requires-Dist: llvmlite
Requires-Dist: einops>=0.4.0
Requires-Dist: performer-pytorch
Requires-Dist: axial-positional-embedding
Requires-Dist: local-attention
Requires-Dist: fair-esm
Requires-Dist: rna-fm
Requires-Dist: pytorch-lightning
Requires-Dist: pytorch-ignite>=0.4.6
Requires-Dist: torchmetrics
Requires-Dist: torchsummary
Requires-Dist: dm-tree
Requires-Dist: biopython~=1.85
Requires-Dist: biotite
Requires-Dist: mygene>=3.2.0
Requires-Dist: biothings-client>=0.2.0
Requires-Dist: tape-proteins
Requires-Dist: transformers
Requires-Dist: tokenizers
Requires-Dist: huggingface-hub
Requires-Dist: sacremoses
Requires-Dist: regex
Requires-Dist: protobuf
Requires-Dist: filelock
Requires-Dist: hydra-core>=1.0.0
Requires-Dist: omegaconf>=2.0.0
Requires-Dist: pydantic>=2.5.0
Requires-Dist: pydantic-settings>=2.1.0
Requires-Dist: python-box>=6.0.0
Requires-Dist: ml-collections>=0.1.0
Requires-Dist: matplotlib>=3.5.0
Requires-Dist: seaborn
Requires-Dist: pillow>=9.0.0
Requires-Dist: contourpy>=1.0.0
Requires-Dist: cycler>=0.11.0
Requires-Dist: fonttools>=4.30.0
Requires-Dist: qmllib
Requires-Dist: requests>=2.26.0
Requires-Dist: aiohttp>=3.8.0
Requires-Dist: yarl
Requires-Dist: frozenlist
Requires-Dist: aiosignal
Requires-Dist: async-timeout
Requires-Dist: charset-normalizer>=2.0.0
Requires-Dist: idna>=3.0
Requires-Dist: urllib3>=1.26.0
Requires-Dist: lxml
Requires-Dist: pandas-datareader
Requires-Dist: opencv-python
Requires-Dist: pyyaml>=6.0.0
Requires-Dist: packaging>=21.0
Requires-Dist: pyparsing>=3.0.0
Requires-Dist: python-dateutil>=2.8.0
Requires-Dist: six>=1.15.0
Requires-Dist: joblib>=1.0.0
Requires-Dist: tabulate>=0.8.9
Requires-Dist: colorama>=0.4.4
Requires-Dist: contextlib2>=21.0.0
Requires-Dist: psutil
Requires-Dist: typing-extensions
Requires-Dist: future
Requires-Dist: attrs
Requires-Dist: more-itertools
Requires-Dist: pluggy
Requires-Dist: py
Requires-Dist: cachetools
Requires-Dist: importlib-metadata
Requires-Dist: importlib-resources
Requires-Dist: setuptools
Requires-Dist: wheel
Requires-Dist: openmm
Requires-Dist: huggingface_hub
Requires-Dist: hf_xet
Requires-Dist: requests>=2.25.0
Requires-Dist: beautifulsoup4>=4.9.0
Requires-Dist: tqdm>=4.60.0
Requires-Dist: cffi
Requires-Dist: pycparser
Requires-Dist: cython
Provides-Extra: dev
Requires-Dist: tqdm>=4.62.0; extra == "dev"
Requires-Dist: absl-py>=1.0.0; extra == "dev"
Requires-Dist: tensorboard>=2.6.0; extra == "dev"
Requires-Dist: tensorboard-data-server>=0.6.0; extra == "dev"
Requires-Dist: tensorboard-plugin-wit>=1.8.0; extra == "dev"
Requires-Dist: tensorboardx; extra == "dev"
Requires-Dist: mypy; extra == "dev"
Requires-Dist: mypy-extensions; extra == "dev"
Requires-Dist: typed-ast; extra == "dev"
Requires-Dist: flake8; extra == "dev"
Requires-Dist: pycodestyle; extra == "dev"
Requires-Dist: pyflakes; extra == "dev"
Requires-Dist: autopep8; extra == "dev"
Requires-Dist: pytest; extra == "dev"
Requires-Dist: ipython-genutils; extra == "dev"
Requires-Dist: jedi; extra == "dev"
Requires-Dist: parso; extra == "dev"
Requires-Dist: jmespath; extra == "dev"
Requires-Dist: decorator; extra == "dev"
Requires-Dist: entrypoints; extra == "dev"
Requires-Dist: prompt-toolkit; extra == "dev"
Requires-Dist: traitlets; extra == "dev"
Requires-Dist: wcwidth; extra == "dev"
Requires-Dist: monkeytype; extra == "dev"
Requires-Dist: pre-commit; extra == "dev"
Requires-Dist: pylint; extra == "dev"
Requires-Dist: pytest-cov; extra == "dev"
Requires-Dist: build; extra == "dev"
Requires-Dist: twine; extra == "dev"
Provides-Extra: jupyter
Requires-Dist: ipykernel; extra == "jupyter"
Requires-Dist: ipython; extra == "jupyter"
Requires-Dist: jupyter; extra == "jupyter"
Requires-Dist: jupyter-client; extra == "jupyter"
Requires-Dist: jupyter-console; extra == "jupyter"
Requires-Dist: jupyter-core; extra == "jupyter"
Requires-Dist: jupyterlab-widgets; extra == "jupyter"
Requires-Dist: widgetsnbextension; extra == "jupyter"
Requires-Dist: ipywidgets; extra == "jupyter"
Requires-Dist: nbclient; extra == "jupyter"
Requires-Dist: nbconvert; extra == "jupyter"
Requires-Dist: nbformat; extra == "jupyter"
Requires-Dist: nest-asyncio; extra == "jupyter"
Requires-Dist: prometheus-client; extra == "jupyter"
Requires-Dist: pygments; extra == "jupyter"
Requires-Dist: bleach; extra == "jupyter"
Requires-Dist: defusedxml; extra == "jupyter"
Requires-Dist: webencodings; extra == "jupyter"
Requires-Dist: markdown; extra == "jupyter"
Requires-Dist: mistune; extra == "jupyter"
Requires-Dist: jsonschema; extra == "jupyter"
Requires-Dist: pyrsistent; extra == "jupyter"
Requires-Dist: pandocfilters; extra == "jupyter"
Requires-Dist: send2trash; extra == "jupyter"
Requires-Dist: terminado; extra == "jupyter"
Requires-Dist: testpath; extra == "jupyter"
Requires-Dist: jupyterlab; extra == "jupyter"
Requires-Dist: jupytext; extra == "jupyter"
Requires-Dist: ipympl; extra == "jupyter"
Provides-Extra: web
Requires-Dist: aiohttp>=3.8.0; extra == "web"
Requires-Dist: yarl; extra == "web"
Requires-Dist: frozenlist; extra == "web"
Requires-Dist: aiosignal; extra == "web"
Requires-Dist: async-timeout; extra == "web"
Requires-Dist: charset-normalizer>=2.0.0; extra == "web"
Requires-Dist: idna>=3.0; extra == "web"
Requires-Dist: urllib3>=1.26.0; extra == "web"
Provides-Extra: cloud
Requires-Dist: google-auth>=1.34.0; extra == "cloud"
Requires-Dist: google-auth-oauthlib; extra == "cloud"
Requires-Dist: oauthlib; extra == "cloud"
Requires-Dist: requests-oauthlib; extra == "cloud"
Requires-Dist: s3transfer; extra == "cloud"
Requires-Dist: boto3; extra == "cloud"
Requires-Dist: botocore; extra == "cloud"
Requires-Dist: rsa; extra == "cloud"
Requires-Dist: pyopenssl; extra == "cloud"
Requires-Dist: cryptography; extra == "cloud"
Requires-Dist: pysocks; extra == "cloud"
Provides-Extra: visualization
Requires-Dist: opencv-python; extra == "visualization"
Requires-Dist: contourpy>=1.0.0; extra == "visualization"
Requires-Dist: cycler>=0.11.0; extra == "visualization"
Requires-Dist: fonttools>=4.30.0; extra == "visualization"
Dynamic: author
Dynamic: home-page
Dynamic: license-file
Dynamic: requires-python
